MyMail/__init__.py
MyMail/mail.py
MyMail-0.0.2.dist-info/METADATA
MyMail-0.0.2.dist-info/WHEEL
MyMail-0.0.2.dist-info/top_level.txt
MyMail-0.0.2.dist-info/RECORD
