Metadata-Version: 2.1
Name: MyMail
Version: 0.0.2
Summary: A small example package By Rahul Pandey
Home-page: https://github.com/rahulpandey81/MyMail
Author: Rahul Pandey
Author-email: rahulpandey.rp1996@gmail.com
License: UNKNOWN
Platform: UNKNOWN
Classifier: Programming Language :: Python :: 3
Classifier: License :: OSI Approved :: MIT License
Classifier: Operating System :: OS Independent
Requires-Python: >=3.6
